nativeconfig/__init__.py
nativeconfig/exceptions.py
nativeconfig/version.py
nativeconfig/configs/__init__.py
nativeconfig/configs/base_config.py
nativeconfig/configs/json_config.py
nativeconfig/configs/memory_config.py
nativeconfig/configs/nsuserdefaults_config.py
nativeconfig/configs/registry_config.py
nativeconfig/configs/yaml_config.py
nativeconfig/options/__init__.py
nativeconfig/options/array_option.py
nativeconfig/options/base_option.py
nativeconfig/options/boolean_option.py
nativeconfig/options/dict_option.py
nativeconfig/options/enum_option.py
nativeconfig/options/float_option.py
nativeconfig/options/int_option.py
nativeconfig/options/path_option.py
nativeconfig/options/string_option.py
nativeconfig-3.4.0.dist-info/DESCRIPTION.rst
nativeconfig-3.4.0.dist-info/METADATA
nativeconfig-3.4.0.dist-info/RECORD
nativeconfig-3.4.0.dist-info/WHEEL
nativeconfig-3.4.0.dist-info/metadata.json
nativeconfig-3.4.0.dist-info/top_level.txt
