Metadata-Version: 2.0
Name: nativeconfig
Version: 3.4.0
Summary: Cross-platform python module to store application config via native subsystems such as Windows Registry or NSUserDefaults.
Home-page: https://github.com/GreatFruitOmsk/nativeconfig
Author: Ilya Kulakov
Author-email: kulakov.ilya@gmail.com
License: MIT License
Keywords: config,winreg,NSUserDefaults
Platform: any
Classifier: Intended Audience :: Developers
Classifier: Intended Audience :: System Administrators
Classifier: License :: OSI Approved :: MIT License
Classifier: Natural Language :: English
Classifier: Operating System :: MacOS :: MacOS X
Classifier: Operating System :: Microsoft :: Windows
Classifier: Operating System :: POSIX :: Linux
Classifier: Programming Language :: Python
Classifier: Programming Language :: Python :: 3
Classifier: Programming Language :: Python :: 3.4
Classifier: Programming Language :: Python :: 3.5
Classifier: Programming Language :: Python :: 3.6
